topological_coherence/__init__.py
topological_coherence-0.1.2.dist-info/METADATA
topological_coherence-0.1.2.dist-info/WHEEL
topological_coherence-0.1.2.dist-info/licenses/LICENSE
topological_coherence-0.1.2.dist-info/RECORD
