Metadata-Version: 2.4
Name: topological-coherence
Version: 0.1.2
Summary: Toroidal attention constraints for reducing LLM hallucination
Project-URL: Homepage, https://github.com/Paraxiom/topological-coherence
Project-URL: Documentation, https://paraxiom.org/presentations/coherence.html
Project-URL: Repository, https://github.com/Paraxiom/topological-coherence
Project-URL: Paper, https://doi.org/10.5281/zenodo.18187835
Author-email: Sylvain Cormier <sylvain@paraxiom.io>
License-Expression: MIT
License-File: LICENSE
Keywords: attention,hallucination,llm,machine-learning,tonnetz,topology,transformer
Classifier: Development Status :: 4 - Beta
Classifier: Intended Audience :: Science/Research
Classifier: License :: OSI Approved :: MIT License
Classifier: Programming Language :: Python :: 3
Classifier: Programming Language :: Python :: 3.9
Classifier: Programming Language :: Python :: 3.10
Classifier: Programming Language :: Python :: 3.11
Classifier: Programming Language :: Python :: 3.12
Classifier: Topic :: Scientific/Engineering :: Artificial Intelligence
Requires-Python: >=3.9
Requires-Dist: numpy>=1.21.0
Requires-Dist: torch>=2.0.0
Provides-Extra: demo
Requires-Dist: gradio>=4.0.0; extra == 'demo'
Provides-Extra: dev
Requires-Dist: black; extra == 'dev'
Requires-Dist: pytest>=7.0.0; extra == 'dev'
Requires-Dist: ruff; extra == 'dev'
